pyvergeos/__init__.py
pyvergeos/__version__.py
pyvergeos/client.py
pyvergeos/connection.py
pyvergeos/exceptions.py
pyvergeos/filters.py
pyvergeos/py.typed
pyvergeos/models/__init__.py
pyvergeos/resources/__init__.py
pyvergeos/resources/alarms.py
pyvergeos/resources/aliases.py
pyvergeos/resources/api_keys.py
pyvergeos/resources/base.py
pyvergeos/resources/certificates.py
pyvergeos/resources/cloud_snapshots.py
pyvergeos/resources/cloudinit_files.py
pyvergeos/resources/clusters.py
pyvergeos/resources/dns.py
pyvergeos/resources/drives.py
pyvergeos/resources/files.py
pyvergeos/resources/groups.py
pyvergeos/resources/hosts.py
pyvergeos/resources/ipsec.py
pyvergeos/resources/logs.py
pyvergeos/resources/nas_cifs.py
pyvergeos/resources/nas_nfs.py
pyvergeos/resources/nas_services.py
pyvergeos/resources/nas_users.py
pyvergeos/resources/nas_volume_browser.py
pyvergeos/resources/nas_volume_syncs.py
pyvergeos/resources/nas_volumes.py
pyvergeos/resources/networks.py
pyvergeos/resources/nics.py
pyvergeos/resources/nodes.py
pyvergeos/resources/permissions.py
pyvergeos/resources/resource_groups.py
pyvergeos/resources/rules.py
pyvergeos/resources/shared_objects.py
pyvergeos/resources/site_syncs.py
pyvergeos/resources/sites.py
pyvergeos/resources/snapshot_profiles.py
pyvergeos/resources/snapshots.py
pyvergeos/resources/storage_tiers.py
pyvergeos/resources/system.py
pyvergeos/resources/tags.py
pyvergeos/resources/tasks.py
pyvergeos/resources/tenant_external_ips.py
pyvergeos/resources/tenant_layer2.py
pyvergeos/resources/tenant_manager.py
pyvergeos/resources/tenant_network_blocks.py
pyvergeos/resources/tenant_nodes.py
pyvergeos/resources/tenant_snapshots.py
pyvergeos/resources/tenant_storage.py
pyvergeos/resources/users.py
pyvergeos/resources/vms.py
pyvergeos/resources/webhooks.py
pyvergeos/resources/wireguard.py
pyvergeos/utils/__init__.py
pyvergeos-0.1.1.dist-info/METADATA
pyvergeos-0.1.1.dist-info/WHEEL
pyvergeos-0.1.1.dist-info/RECORD
