Metadata-Version: 2.4
Name: pyvergeos
Version: 0.1.1
Summary: Python SDK for the VergeOS REST API
Project-URL: Homepage, https://github.com/verge-io/pyvergeos
Project-URL: Documentation, https://github.com/verge-io/pyvergeos#readme
Project-URL: Repository, https://github.com/verge-io/pyvergeos
Project-URL: Issues, https://github.com/verge-io/pyvergeos/issues
Author-email: "Verge.io" <support@verge.io>
License: MIT
Keywords: api,cloud,sdk,verge,vergeos,virtualization
Classifier: Development Status :: 3 - Alpha
Classifier: Intended Audience :: Developers
Classifier: Intended Audience :: System Administrators
Classifier: License :: OSI Approved :: MIT License
Classifier: Operating System :: OS Independent
Classifier: Programming Language :: Python :: 3
Classifier: Programming Language :: Python :: 3.9
Classifier: Programming Language :: Python :: 3.10
Classifier: Programming Language :: Python :: 3.11
Classifier: Programming Language :: Python :: 3.12
Classifier: Programming Language :: Python :: 3.13
Classifier: Topic :: Software Development :: Libraries :: Python Modules
Classifier: Topic :: System :: Systems Administration
Classifier: Typing :: Typed
Requires-Python: >=3.9
Requires-Dist: requests>=2.28.0
Provides-Extra: all
Requires-Dist: httpx>=0.24.0; extra == 'all'
Requires-Dist: pydantic>=2.0; extra == 'all'
Provides-Extra: async
Requires-Dist: httpx>=0.24.0; extra == 'async'
Provides-Extra: pydantic
Requires-Dist: pydantic>=2.0; extra == 'pydantic'
